{"id":"MDX4TXYD84UCZ","name":"@-Nightcrow- 的个人主页 - 微博","size":212759,"btime":1754313279823,"mtime":1754313279916,"ext":"jpg","tags":[],"folders":["M0IUIV1O60XH8"],"isDeleted":false,"url":"https://weibo.com/u/3195843380?tabtype=album&uid=3195843380&index=1","annotation":"","modificationTime":1754313279781,"height":1530,"width":1000,"lastModified":1754313280139,"palettes":[{"color":[248,249,246],"ratio":65},{"color":[223,218,156],"ratio":8},{"color":[85,86,106],"ratio":6},{"color":[157,172,173],"ratio":6},{"color":[203,177,106],"ratio":5},{"color":[202,222,215],"ratio":4.02},{"color":[143,123,146],"ratio":1.34},{"color":[142,82,85],"ratio":0.93},{"color":[200,180,202],"ratio":0.44},{"color":[97,140,202],"ratio":0.36}]}