{"id":"M2ZNRO2N0UM3E","name":"算法导论_原书第3版_CHS","size":103966257,"btime":1731247452468,"mtime":1731247452521,"ext":"pdf","tags":[],"folders":["LZS3VQ63WF737"],"isDeleted":false,"url":"","annotation":"","modificationTime":1730521413023,"width":489,"height":733,"lastModified":1741973796322,"palettes":[{"color":[222,222,222],"ratio":58,"$$hashKey":"object:1356"},{"color":[124,124,124],"ratio":18,"$$hashKey":"object:1362"},{"color":[108,108,108],"ratio":4.28,"$$hashKey":"object:1363"},{"color":[176,176,176],"ratio":3.77,"$$hashKey":"object:1358"},{"color":[47,47,47],"ratio":3.69,"$$hashKey":"object:1365"},{"color":[188,188,188],"ratio":3.38,"$$hashKey":"object:1357"},{"color":[100,100,100],"ratio":1.95,"$$hashKey":"object:1364"},{"color":[156,156,156],"ratio":1.9,"$$hashKey":"object:1360"},{"color":[164,164,164],"ratio":1.86,"$$hashKey":"object:1359"},{"color":[148,148,148],"ratio":1.62,"$$hashKey":"object:1361"},{"color":[92,92,92],"ratio":1}],"order":{"LZS3VQ63WF737":"1728529772239.375"}}