{"id":"M3FRF32CTOHUR","name":"微博 – 随时随地发现新鲜事","size":376997,"btime":1731495003221,"mtime":1731495003366,"ext":"jpg","tags":[],"folders":["M0IUIV1O60XH8"],"isDeleted":false,"url":"https://weibo.com/5266164510/P07SP7JaH","annotation":"","modificationTime":1731495003204,"height":882,"width":1250,"lastModified":1731495003521,"palettes":[{"color":[54,49,33],"ratio":52},{"color":[133,103,62],"ratio":15},{"color":[99,78,44],"ratio":14},{"color":[180,158,115],"ratio":12},{"color":[13,31,27],"ratio":4.32},{"color":[106,100,68],"ratio":0.34}]}